ignot/__init__.py
ignot/bundle.py
ignot/cli.py
ignot/models.py
ignot/data/authlib.json
ignot/data/liteloader.json
ignot/data/vanilla.json
ignot-0.1.1.dist-info/AUTHORS.rst
ignot-0.1.1.dist-info/LICENSE
ignot-0.1.1.dist-info/METADATA
ignot-0.1.1.dist-info/WHEEL
ignot-0.1.1.dist-info/entry_points.txt
ignot-0.1.1.dist-info/top_level.txt
ignot-0.1.1.dist-info/RECORD
