Metadata-Version: 2.1
Name: ignot
Version: 0.1.1
Summary: Simple CLI for MC versions management
Home-page: https://git.mc4ep.org/mc4ep/ignot
Author: Andriy Kushnir (Orhideous)
Author-email: me@orhideous.name
License: MIT license
Keywords: Minecraft,modpack,skcraft
Platform: UNKNOWN
Classifier: Development Status :: 4 - Beta
Classifier: Intended Audience :: Developers
Classifier: License :: OSI Approved :: MIT License
Classifier: Natural Language :: English
Classifier: Programming Language :: Python :: 3.6
Requires-Dist: pydantic (==0.32.2)
Requires-Dist: yamlcfg (==0.5.3)
Requires-Dist: click (==7.0)
Requires-Dist: requests (==2.22.0)
Requires-Dist: pytz (==2019.3)
